lm_raindrop/__init__.py
lm_raindrop/_base_client.py
lm_raindrop/_client.py
lm_raindrop/_compat.py
lm_raindrop/_constants.py
lm_raindrop/_exceptions.py
lm_raindrop/_files.py
lm_raindrop/_models.py
lm_raindrop/_qs.py
lm_raindrop/_resource.py
lm_raindrop/_response.py
lm_raindrop/_streaming.py
lm_raindrop/_types.py
lm_raindrop/_version.py
lm_raindrop/py.typed
lm_raindrop/_utils/__init__.py
lm_raindrop/_utils/_logs.py
lm_raindrop/_utils/_proxy.py
lm_raindrop/_utils/_reflection.py
lm_raindrop/_utils/_streams.py
lm_raindrop/_utils/_sync.py
lm_raindrop/_utils/_transform.py
lm_raindrop/_utils/_typing.py
lm_raindrop/_utils/_utils.py
lm_raindrop/lib/.keep
lm_raindrop/resources/__init__.py
lm_raindrop/resources/chunk_search.py
lm_raindrop/resources/document_query.py
lm_raindrop/resources/object.py
lm_raindrop/resources/search.py
lm_raindrop/resources/summarize_page.py
lm_raindrop/types/__init__.py
lm_raindrop/types/chunk_search_create_params.py
lm_raindrop/types/chunk_search_create_response.py
lm_raindrop/types/document_query_create_params.py
lm_raindrop/types/document_query_create_response.py
lm_raindrop/types/object_delete_response.py
lm_raindrop/types/object_upload_params.py
lm_raindrop/types/object_upload_response.py
lm_raindrop/types/search_get_results_params.py
lm_raindrop/types/search_perform_params.py
lm_raindrop/types/search_response.py
lm_raindrop/types/summarize_page_create_params.py
lm_raindrop/types/summarize_page_create_response.py
lm_raindrop/types/text_result.py
lm_raindrop-1.0.0.dist-info/METADATA
lm_raindrop-1.0.0.dist-info/WHEEL
lm_raindrop-1.0.0.dist-info/licenses/LICENSE
lm_raindrop-1.0.0.dist-info/RECORD
